carton/__init__.py
carton/collections.py
carton/data.py
carton/datetime.py
carton/file.py
carton/gallary.py
carton/io.py
carton/logger.py
carton/palette.py
carton/pandas_.py
carton/params.py
carton/py.typed
carton/random.py
carton/utils.py
pycarton-0.3.8.dist-info/WHEEL
pycarton-0.3.8.dist-info/METADATA
pycarton-0.3.8.dist-info/RECORD
