Metadata-Version: 2.1
Name: pycarton
Version: 0.3.8
Summary: Python toolbox.
Author: Yevgnen Koh
Author-email: wherejoystarts@gmail.com
Requires-Python: >=3.8,<4.0
Classifier: Programming Language :: Python :: 3
Classifier: Programming Language :: Python :: 3.8
Classifier: Programming Language :: Python :: 3.9
Classifier: Programming Language :: Python :: 3.10
Requires-Dist: numpy (>=1.22.3,<2.0.0)
Requires-Dist: pytoml (>=0.1.21,<0.2.0)
Requires-Dist: ruyaml (>=0.91.0,<0.92.0)
